COPYING
MANIFEST.in
README.rst
setup.py
bin/chore.sacct
bin/chore.sbatch
bin/chore.scancel
bin/chore.watch
chore/__init__.py
chore/base.py
chore/fake.py
chore/lsf.py
chore/shell.py
chore/slurm.py
chore.egg-info/PKG-INFO
chore.egg-info/SOURCES.txt
chore.egg-info/dependency_links.txt
chore.egg-info/requires.txt
chore.egg-info/top_level.txt
tests/__init__.py
tests/test_base.py
tests/test_shell.py
tests/test_slurm.py
tests/utils.py