Metadata-Version: 1.1
Name: chore
Version: 0.8.6
Summary: Multi-scheduler job dispatcher
Home-page: https://gitlab.com/doctormo/python-chore
Author: Martin Owens
Author-email: doctormo@gmail.com
License: LGPLv3
Platform: linux
Classifier: Intended Audience :: Developers
Classifier: Intended Audience :: Information Technology
Classifier: Intended Audience :: System Administrators
Classifier: License :: OSI Approved :: GNU Lesser General Public License v3 or later (LGPLv3+)
Classifier: Operating System :: POSIX
Classifier: Operating System :: POSIX :: Linux
Classifier: Programming Language :: Python
Classifier: Programming Language :: Python :: 2.7
Classifier: Programming Language :: Python :: 3.6
